mecab/__init__.py
mecab/data_structure.py
mecab/lattice.py
mecab/mecab.py
mecab/model.py
mecab/tagger.py
pecab-0.0.dist-info/METADATA
pecab-0.0.dist-info/WHEEL
pecab-0.0.dist-info/top_level.txt
pecab-0.0.dist-info/RECORD
