Metadata-Version: 2.1
Name: pecab
Version: 0.0
Summary: Pure python mecab analyzer for Korean & Japanese
Home-page: https://github.com/hyunwoongko/kss
Author: Hyunwoong Ko
Author-email: kevin.woong@kakaobrain.com
License: Apache 2.0
Platform: any
Classifier: Programming Language :: Python :: 3
Classifier: Programming Language :: Python :: 3.2
Classifier: Programming Language :: Python :: 3.3
Classifier: Programming Language :: Python :: 3.4
Classifier: Programming Language :: Python :: 3.5
Classifier: Programming Language :: Python :: 3.6
Classifier: Programming Language :: Python :: 3.7
Classifier: Programming Language :: Python :: 3.8
Classifier: Programming Language :: Python :: 3.9
Requires-Python: >=3
